kelogger/__init__.py
kelogger/logger.py
kelogger-0.5.0.dist-info/METADATA
kelogger-0.5.0.dist-info/WHEEL
kelogger-0.5.0.dist-info/top_level.txt
kelogger-0.5.0.dist-info/RECORD
